README.rst
setup.cfg
setup.py
ufinance/__init__.py
ufinance/history.py
ufinance.egg-info/PKG-INFO
ufinance.egg-info/SOURCES.txt
ufinance.egg-info/dependency_links.txt
ufinance.egg-info/requires.txt
ufinance.egg-info/top_level.txt