Metadata-Version: 1.1
Name: ufinance
Version: 0.0.1
Summary: UNIST Finance Tool
Home-page: https://github.com/koorukuroo/ufinance
Author: Kyunghoon Kim
Author-email: kyunghoon@unist.ac.kr
License: MIT License
Keywords: Finance,Stock,Pandas
Platform: UNKNOWN
Classifier: Programming Language :: Python
Classifier: License :: OSI Approved :: MIT License
Classifier: Topic :: Software Development :: Libraries :: Python Modules
